liverun/__init__.py
liverun/__main__.py
liverun/cli.py
liverun/file_change_runner.py
liverun/log_utils.py
liverun-0.1.1.dist-info/METADATA
liverun-0.1.1.dist-info/WHEEL
liverun-0.1.1.dist-info/entry_points.txt
liverun-0.1.1.dist-info/top_level.txt
liverun-0.1.1.dist-info/RECORD
