Metadata-Version: 2.4
Name: liverun
Version: 0.1.1
Summary: A simple CLI tool to run commands on file changes.
Author: Julynx
License-Expression: GPL-2.0-only
Project-URL: Homepage, https://github.com/Julynx/liverun
Project-URL: Repository, https://github.com/Julynx/liverun
Keywords: file watcher,cli,devtools,livereload,python
Classifier: Programming Language :: Python :: 3
Classifier: Programming Language :: Python :: 3 :: Only
Classifier: Programming Language :: Python :: 3.11
Classifier: Programming Language :: Python :: 3.12
Classifier: Programming Language :: Python :: 3.13
Classifier: Environment :: Console
Classifier: Intended Audience :: Developers
Classifier: Operating System :: OS Independent
Classifier: Topic :: Utilities
Classifier: Topic :: Software Development :: Build Tools
Requires-Python: >=3.11
